skg/__init__.py
skg/citeproc.py
skg/crossref.py
skg/dblp.py
skg/doi.py
skg/event.py
skg/graph.py
skg/kg.py
skg/location.py
skg/orcid.py
skg/owl.py
skg/paper.py
skg/profiler.py
skg/schema.py
skg/scholar.py
skg/scholargrid.py
skg/search.py
skg/searchengine.py
skg/semantic_scholar.py
skg/skgbrowser.py
skg/smw.py
skg/sotsog.py
skg/version.py
skg/wdsearch.py
skg/wikidata.py
skg/resources/static/css/md_style_indigo.css
pysotsog-0.1.5.dist-info/METADATA
pysotsog-0.1.5.dist-info/WHEEL
pysotsog-0.1.5.dist-info/entry_points.txt
pysotsog-0.1.5.dist-info/licenses/LICENSE
pysotsog-0.1.5.dist-info/RECORD
