Metadata-Version: 2.1
Name: pysotsog
Version: 0.1.5
Project-URL: Home, https://github.com/WolfgangFahl/pysotsog
Project-URL: Documentation, https://wiki.bitplan.com/index.php/Pysotsog
Project-URL: Source, https://github.com/WolfgangFahl/pysotsog
Author-email: Wolfgang Fahl <wf@bitplan.com>
Maintainer-email: Wolfgang Fahl <wf@bitplan.com>
License-Expression: Apache-2.0
License-File: LICENSE
Classifier: Development Status :: 4 - Beta
Classifier: Environment :: Web Environment
Classifier: Intended Audience :: Developers
Classifier: Intended Audience :: Education
Classifier: Intended Audience :: Science/Research
Classifier: License :: OSI Approved :: Apache Software License
Classifier: Operating System :: OS Independent
Classifier: Programming Language :: Python :: 3 :: Only
Classifier: Programming Language :: Python :: 3.8
Classifier: Programming Language :: Python :: 3.9
Classifier: Programming Language :: Python :: 3.10
Classifier: Programming Language :: Python :: 3.11
Classifier: Topic :: Software Development :: User Interfaces
Requires-Python: >=3.8
Requires-Dist: fake-useragent>=0.1.11
Requires-Dist: habanero~=1.2.2
Requires-Dist: justpy>=0.12.1
Requires-Dist: py-3rdparty-mediawiki>=0.8.1
Requires-Dist: pyjustpywidgets>=0.1.11
Requires-Dist: pylodstorage>=0.4.7
Requires-Dist: pyonlinespreadsheetediting>=0.1.1
Requires-Dist: python-stdnum>=1.18
Requires-Dist: search-engine-parser>=0.6.8
Requires-Dist: semanticscholar>=0.3.0
Provides-Extra: test
Requires-Dist: green; extra == 'test'
